{
    "nodes": [
        {
            "id": 0,
            "x": 22.164157084436432,
            "y": 37.02280948805595,
            "type": "path",
            "radius": 3.3364099151528737,
            "paths": [
                0
            ],
            "children": [],
            "index": 0,
            "vy": 0.0004806888969579968,
            "vx": 0.0002862179394969057,
            "parent": 24
        },
        {
            "id": 1,
            "x": 9.349327502092788,
            "y": 16.037713185739484,
            "type": "path",
            "radius": 3.165646729342825,
            "paths": [
                1
            ],
            "children": [],
            "index": 1,
            "vy": 0.0009843927444493784,
            "vx": -0.000559770902959271,
            "parent": 24
        },
        {
            "id": 2,
            "x": 50.11058933056635,
            "y": 3.0169734943163005,
            "type": "path",
            "radius": 3.0208333333333335,
            "paths": [
                2
            ],
            "children": [],
            "index": 2,
            "vy": -0.003859839017033214,
            "vx": -0.0012080100331286002,
            "parent": 23
        },
        {
            "id": 3,
            "x": 66.06377092269149,
            "y": 51.2021452560885,
            "type": "path",
            "radius": 3.8902816708484216,
            "paths": [
                3
            ],
            "children": [],
            "index": 3,
            "vy": -0.0007623278297416866,
            "vx": 0.00016410350342822635,
            "parent": 21
        },
        {
            "id": 4,
            "x": 68.66603708058649,
            "y": 43.718008981580525,
            "type": "path",
            "radius": 3.349741992477917,
            "paths": [
                4
            ],
            "children": [],
            "index": 4,
            "vy": -0.0006490604550815181,
            "vx": 0.015779073064404476,
            "parent": 21
        },
        {
            "id": 5,
            "x": 37.98888574610562,
            "y": 68.99852552074883,
            "type": "path",
            "radius": 3.009259259259259,
            "paths": [
                5
            ],
            "children": [],
            "index": 5,
            "vy": 0.007784780008074595,
            "vx": 0.0004923682621674706,
            "parent": 20
        },
        {
            "id": 6,
            "x": 30.72820983630991,
            "y": 66.11097931047091,
            "type": "path",
            "radius": 3.009259259259259,
            "paths": [
                6
            ],
            "children": [],
            "index": 6,
            "vy": 0.0007349489016690545,
            "vx": 0.0003193703379191845,
            "parent": 20
        },
        {
            "id": 7,
            "x": 29.2228861704569,
            "y": 57.656800600058034,
            "type": "path",
            "radius": 3.0127454905793787,
            "paths": [
                7
            ],
            "children": [],
            "index": 7,
            "vy": 0.0006889606092086032,
            "vx": 5.123449811463409e-05,
            "parent": 20
        },
        {
            "id": 8,
            "x": 47.01770860100127,
            "y": 68.6536616997937,
            "type": "path",
            "radius": 3.3511934864046555,
            "paths": [
                8
            ],
            "children": [],
            "index": 8,
            "vy": 0.004855186198350763,
            "vx": 0.0012305672629168596,
            "parent": 20
        },
        {
            "id": 9,
            "x": 12.868535699275908,
            "y": 40.77441339555159,
            "type": "path",
            "radius": 3.0343366529559717,
            "paths": [
                9
            ],
            "children": [],
            "index": 9,
            "vy": 0.001004402142779605,
            "vx": 6.366031245587135e-05,
            "parent": 24
        },
        {
            "id": 10,
            "x": 18.43236558969484,
            "y": 16.304339192126484,
            "type": "path",
            "radius": 3.0203161477631966,
            "paths": [
                10
            ],
            "children": [],
            "index": 10,
            "vy": 0.0006980658125653426,
            "vx": -0.0011264675451355705,
            "parent": 24
        },
        {
            "id": 11,
            "x": 3.158581503572067,
            "y": 22.17370365383446,
            "type": "path",
            "radius": 3.0390544910453543,
            "paths": [
                11
            ],
            "children": [],
            "index": 11,
            "vy": 0.0009906649634875387,
            "vx": -0.0005945408419398529,
            "parent": 24
        },
        {
            "id": 12,
            "x": 52.76201142902464,
            "y": 62.51013246602108,
            "type": "path",
            "radius": 3.101919973213165,
            "paths": [
                12
            ],
            "children": [],
            "index": 12,
            "vy": -4.3046510854458095e-05,
            "vx": 0.0003792510575673161,
            "parent": 20
        },
        {
            "id": 13,
            "x": 68.23841043134162,
            "y": 31.909046048604903,
            "type": "path",
            "radius": 3.7647254639188623,
            "paths": [
                13
            ],
            "children": [],
            "index": 13,
            "vy": -0.0005272400523044829,
            "vx": 0.003135895260481715,
            "parent": 21
        },
        {
            "id": 14,
            "x": 30.121330282550286,
            "y": 3.014955658710269,
            "type": "path",
            "radius": 3.0208333333333335,
            "paths": [
                14
            ],
            "children": [],
            "index": 14,
            "vy": -0.005877674623064368,
            "vx": -0.00015937594982483221,
            "parent": 23
        },
        {
            "id": 15,
            "x": 48.07172555713015,
            "y": 18.64029644405781,
            "type": "path",
            "radius": 3.013407163191527,
            "paths": [
                15
            ],
            "children": [],
            "index": 15,
            "vy": 0.0003310907403079034,
            "vx": -0.00021438707746791516,
            "parent": 23
        },
        {
            "id": 16,
            "x": 43.77430352192185,
            "y": 3.0121755429835164,
            "type": "path",
            "radius": 3.032239967474231,
            "paths": [
                16
            ],
            "children": [],
            "index": 16,
            "vy": -0.02006442449071481,
            "vx": -0.0010906116801028605,
            "parent": 23
        },
        {
            "id": 17,
            "x": 52.51913687723493,
            "y": 10.616032338538629,
            "type": "path",
            "radius": 3.021686483736504,
            "paths": [
                17
            ],
            "children": [],
            "index": 17,
            "vy": -0.00024203937469974464,
            "vx": -0.00024095020477386264,
            "parent": 23
        },
        {
            "id": 18,
            "x": 3.031255950072957,
            "y": 30.51999037279538,
            "type": "path",
            "radius": 3.0364496179042564,
            "paths": [
                18
            ],
            "children": [],
            "index": 18,
            "vy": 0.0010700578101138513,
            "vx": -0.005193667831299571,
            "parent": 24
        },
        {
            "id": 19,
            "x": 5.571732442716168,
            "y": 37.698602851189335,
            "type": "path",
            "radius": 3.0355656163425615,
            "paths": [
                19
            ],
            "children": [],
            "index": 19,
            "vy": 0.0011370105522622372,
            "vx": -0.0002570825902962745,
            "parent": 24
        },
        {
            "id": 20,
            "x": 41.38815569069516,
            "y": 57.88048855465004,
            "type": "group",
            "radius": 3.3511934864046555,
            "paths": [
                12,
                5,
                6,
                7,
                8
            ],
            "children": [
                8,
                12,
                7,
                5,
                6
            ],
            "index": 20,
            "vy": 0.000331749574184053,
            "vx": 0.0001554164805390835,
            "parent": 22
        },
        {
            "id": 21,
            "x": 59.40823748843931,
            "y": 40.22831712339439,
            "type": "group",
            "radius": 3.8902816708484216,
            "paths": [
                13,
                3,
                4
            ],
            "children": [
                4,
                13,
                3
            ],
            "index": 21,
            "vy": -0.0009317903283491517,
            "vx": -0.0002500252392590198,
            "parent": 22
        },
        {
            "id": 22,
            "x": 43.87703370659623,
            "y": 41.09248499195491,
            "type": "group",
            "radius": 3.8902816708484216,
            "paths": [
                12,
                13,
                3,
                4,
                5,
                6,
                7,
                8
            ],
            "children": [
                21,
                20
            ],
            "index": 22,
            "vy": -9.45786179647498e-05,
            "vx": -0.0001867495404099308,
            "parent": 25
        },
        {
            "id": 23,
            "x": 38.93637264047875,
            "y": 10.778939527320984,
            "type": "group",
            "radius": 3.2737067129324986,
            "paths": [
                14,
                15,
                16,
                17,
                2
            ],
            "children": [
                16,
                17,
                15,
                14,
                2
            ],
            "index": 23,
            "vy": 0.000848368278885057,
            "vx": -0.0005681176317642404,
            "parent": 25
        },
        {
            "id": 24,
            "x": 15.017053076537147,
            "y": 27.808935448410676,
            "type": "group",
            "radius": 3.336720508933034,
            "paths": [
                0,
                1,
                10,
                11,
                18,
                19,
                9
            ],
            "children": [
                9,
                1,
                11,
                18,
                19,
                10,
                0
            ],
            "index": 24,
            "vy": 0.000970366892198092,
            "vx": -0.0004286054698255097,
            "parent": 25
        },
        {
            "id": 25,
            "x": 32.57511409020525,
            "y": 24.42329898792903,
            "type": "group",
            "radius": 4.146778584144529,
            "paths": [
                0,
                1,
                10,
                11,
                12,
                13,
                14,
                15,
                16,
                17,
                18,
                19,
                2,
                3,
                4,
                5,
                6,
                7,
                8,
                9
            ],
            "children": [
                22,
                23,
                24
            ],
            "index": 25,
            "vy": 0.0014909798155931255,
            "vx": -0.0004720079220475584
        }
    ],
    "links": [
        {
            "source": {
                "id": 20,
                "x": 41.38815569069516,
                "y": 57.88048855465004,
                "type": "group",
                "radius": 3.3511934864046555,
                "paths": [
                    12,
                    5,
                    6,
                    7,
                    8
                ],
                "children": [
                    8,
                    12,
                    7,
                    5,
                    6
                ],
                "index": 20,
                "vy": 0.000331749574184053,
                "vx": 0.0001554164805390835,
                "parent": 22
            },
            "target": {
                "id": 8,
                "x": 47.01770860100127,
                "y": 68.6536616997937,
                "type": "path",
                "radius": 3.3511934864046555,
                "paths": [
                    8
                ],
                "children": [],
                "index": 8,
                "vy": 0.004855186198350763,
                "vx": 0.0012305672629168596,
                "parent": 20
            },
            "type": "group",
            "index": 0
        },
        {
            "source": {
                "id": 20,
                "x": 41.38815569069516,
                "y": 57.88048855465004,
                "type": "group",
                "radius": 3.3511934864046555,
                "paths": [
                    12,
                    5,
                    6,
                    7,
                    8
                ],
                "children": [
                    8,
                    12,
                    7,
                    5,
                    6
                ],
                "index": 20,
                "vy": 0.000331749574184053,
                "vx": 0.0001554164805390835,
                "parent": 22
            },
            "target": {
                "id": 12,
                "x": 52.76201142902464,
                "y": 62.51013246602108,
                "type": "path",
                "radius": 3.101919973213165,
                "paths": [
                    12
                ],
                "children": [],
                "index": 12,
                "vy": -4.3046510854458095e-05,
                "vx": 0.0003792510575673161,
                "parent": 20
            },
            "type": "group",
            "index": 1
        },
        {
            "source": {
                "id": 20,
                "x": 41.38815569069516,
                "y": 57.88048855465004,
                "type": "group",
                "radius": 3.3511934864046555,
                "paths": [
                    12,
                    5,
                    6,
                    7,
                    8
                ],
                "children": [
                    8,
                    12,
                    7,
                    5,
                    6
                ],
                "index": 20,
                "vy": 0.000331749574184053,
                "vx": 0.0001554164805390835,
                "parent": 22
            },
            "target": {
                "id": 7,
                "x": 29.2228861704569,
                "y": 57.656800600058034,
                "type": "path",
                "radius": 3.0127454905793787,
                "paths": [
                    7
                ],
                "children": [],
                "index": 7,
                "vy": 0.0006889606092086032,
                "vx": 5.123449811463409e-05,
                "parent": 20
            },
            "type": "group",
            "index": 2
        },
        {
            "source": {
                "id": 20,
                "x": 41.38815569069516,
                "y": 57.88048855465004,
                "type": "group",
                "radius": 3.3511934864046555,
                "paths": [
                    12,
                    5,
                    6,
                    7,
                    8
                ],
                "children": [
                    8,
                    12,
                    7,
                    5,
                    6
                ],
                "index": 20,
                "vy": 0.000331749574184053,
                "vx": 0.0001554164805390835,
                "parent": 22
            },
            "target": {
                "id": 5,
                "x": 37.98888574610562,
                "y": 68.99852552074883,
                "type": "path",
                "radius": 3.009259259259259,
                "paths": [
                    5
                ],
                "children": [],
                "index": 5,
                "vy": 0.007784780008074595,
                "vx": 0.0004923682621674706,
                "parent": 20
            },
            "type": "group",
            "index": 3
        },
        {
            "source": {
                "id": 20,
                "x": 41.38815569069516,
                "y": 57.88048855465004,
                "type": "group",
                "radius": 3.3511934864046555,
                "paths": [
                    12,
                    5,
                    6,
                    7,
                    8
                ],
                "children": [
                    8,
                    12,
                    7,
                    5,
                    6
                ],
                "index": 20,
                "vy": 0.000331749574184053,
                "vx": 0.0001554164805390835,
                "parent": 22
            },
            "target": {
                "id": 6,
                "x": 30.72820983630991,
                "y": 66.11097931047091,
                "type": "path",
                "radius": 3.009259259259259,
                "paths": [
                    6
                ],
                "children": [],
                "index": 6,
                "vy": 0.0007349489016690545,
                "vx": 0.0003193703379191845,
                "parent": 20
            },
            "type": "group",
            "index": 4
        },
        {
            "source": {
                "id": 21,
                "x": 59.40823748843931,
                "y": 40.22831712339439,
                "type": "group",
                "radius": 3.8902816708484216,
                "paths": [
                    13,
                    3,
                    4
                ],
                "children": [
                    4,
                    13,
                    3
                ],
                "index": 21,
                "vy": -0.0009317903283491517,
                "vx": -0.0002500252392590198,
                "parent": 22
            },
            "target": {
                "id": 4,
                "x": 68.66603708058649,
                "y": 43.718008981580525,
                "type": "path",
                "radius": 3.349741992477917,
                "paths": [
                    4
                ],
                "children": [],
                "index": 4,
                "vy": -0.0006490604550815181,
                "vx": 0.015779073064404476,
                "parent": 21
            },
            "type": "group",
            "index": 5
        },
        {
            "source": {
                "id": 21,
                "x": 59.40823748843931,
                "y": 40.22831712339439,
                "type": "group",
                "radius": 3.8902816708484216,
                "paths": [
                    13,
                    3,
                    4
                ],
                "children": [
                    4,
                    13,
                    3
                ],
                "index": 21,
                "vy": -0.0009317903283491517,
                "vx": -0.0002500252392590198,
                "parent": 22
            },
            "target": {
                "id": 13,
                "x": 68.23841043134162,
                "y": 31.909046048604903,
                "type": "path",
                "radius": 3.7647254639188623,
                "paths": [
                    13
                ],
                "children": [],
                "index": 13,
                "vy": -0.0005272400523044829,
                "vx": 0.003135895260481715,
                "parent": 21
            },
            "type": "group",
            "index": 6
        },
        {
            "source": {
                "id": 21,
                "x": 59.40823748843931,
                "y": 40.22831712339439,
                "type": "group",
                "radius": 3.8902816708484216,
                "paths": [
                    13,
                    3,
                    4
                ],
                "children": [
                    4,
                    13,
                    3
                ],
                "index": 21,
                "vy": -0.0009317903283491517,
                "vx": -0.0002500252392590198,
                "parent": 22
            },
            "target": {
                "id": 3,
                "x": 66.06377092269149,
                "y": 51.2021452560885,
                "type": "path",
                "radius": 3.8902816708484216,
                "paths": [
                    3
                ],
                "children": [],
                "index": 3,
                "vy": -0.0007623278297416866,
                "vx": 0.00016410350342822635,
                "parent": 21
            },
            "type": "group",
            "index": 7
        },
        {
            "source": {
                "id": 22,
                "x": 43.87703370659623,
                "y": 41.09248499195491,
                "type": "group",
                "radius": 3.8902816708484216,
                "paths": [
                    12,
                    13,
                    3,
                    4,
                    5,
                    6,
                    7,
                    8
                ],
                "children": [
                    21,
                    20
                ],
                "index": 22,
                "vy": -9.45786179647498e-05,
                "vx": -0.0001867495404099308,
                "parent": 25
            },
            "target": {
                "id": 21,
                "x": 59.40823748843931,
                "y": 40.22831712339439,
                "type": "group",
                "radius": 3.8902816708484216,
                "paths": [
                    13,
                    3,
                    4
                ],
                "children": [
                    4,
                    13,
                    3
                ],
                "index": 21,
                "vy": -0.0009317903283491517,
                "vx": -0.0002500252392590198,
                "parent": 22
            },
            "type": "group",
            "index": 8
        },
        {
            "source": {
                "id": 22,
                "x": 43.87703370659623,
                "y": 41.09248499195491,
                "type": "group",
                "radius": 3.8902816708484216,
                "paths": [
                    12,
                    13,
                    3,
                    4,
                    5,
                    6,
                    7,
                    8
                ],
                "children": [
                    21,
                    20
                ],
                "index": 22,
                "vy": -9.45786179647498e-05,
                "vx": -0.0001867495404099308,
                "parent": 25
            },
            "target": {
                "id": 20,
                "x": 41.38815569069516,
                "y": 57.88048855465004,
                "type": "group",
                "radius": 3.3511934864046555,
                "paths": [
                    12,
                    5,
                    6,
                    7,
                    8
                ],
                "children": [
                    8,
                    12,
                    7,
                    5,
                    6
                ],
                "index": 20,
                "vy": 0.000331749574184053,
                "vx": 0.0001554164805390835,
                "parent": 22
            },
            "type": "group",
            "index": 9
        },
        {
            "source": {
                "id": 23,
                "x": 38.93637264047875,
                "y": 10.778939527320984,
                "type": "group",
                "radius": 3.2737067129324986,
                "paths": [
                    14,
                    15,
                    16,
                    17,
                    2
                ],
                "children": [
                    16,
                    17,
                    15,
                    14,
                    2
                ],
                "index": 23,
                "vy": 0.000848368278885057,
                "vx": -0.0005681176317642404,
                "parent": 25
            },
            "target": {
                "id": 16,
                "x": 43.77430352192185,
                "y": 3.0121755429835164,
                "type": "path",
                "radius": 3.032239967474231,
                "paths": [
                    16
                ],
                "children": [],
                "index": 16,
                "vy": -0.02006442449071481,
                "vx": -0.0010906116801028605,
                "parent": 23
            },
            "type": "group",
            "index": 10
        },
        {
            "source": {
                "id": 23,
                "x": 38.93637264047875,
                "y": 10.778939527320984,
                "type": "group",
                "radius": 3.2737067129324986,
                "paths": [
                    14,
                    15,
                    16,
                    17,
                    2
                ],
                "children": [
                    16,
                    17,
                    15,
                    14,
                    2
                ],
                "index": 23,
                "vy": 0.000848368278885057,
                "vx": -0.0005681176317642404,
                "parent": 25
            },
            "target": {
                "id": 17,
                "x": 52.51913687723493,
                "y": 10.616032338538629,
                "type": "path",
                "radius": 3.021686483736504,
                "paths": [
                    17
                ],
                "children": [],
                "index": 17,
                "vy": -0.00024203937469974464,
                "vx": -0.00024095020477386264,
                "parent": 23
            },
            "type": "group",
            "index": 11
        },
        {
            "source": {
                "id": 23,
                "x": 38.93637264047875,
                "y": 10.778939527320984,
                "type": "group",
                "radius": 3.2737067129324986,
                "paths": [
                    14,
                    15,
                    16,
                    17,
                    2
                ],
                "children": [
                    16,
                    17,
                    15,
                    14,
                    2
                ],
                "index": 23,
                "vy": 0.000848368278885057,
                "vx": -0.0005681176317642404,
                "parent": 25
            },
            "target": {
                "id": 15,
                "x": 48.07172555713015,
                "y": 18.64029644405781,
                "type": "path",
                "radius": 3.013407163191527,
                "paths": [
                    15
                ],
                "children": [],
                "index": 15,
                "vy": 0.0003310907403079034,
                "vx": -0.00021438707746791516,
                "parent": 23
            },
            "type": "group",
            "index": 12
        },
        {
            "source": {
                "id": 23,
                "x": 38.93637264047875,
                "y": 10.778939527320984,
                "type": "group",
                "radius": 3.2737067129324986,
                "paths": [
                    14,
                    15,
                    16,
                    17,
                    2
                ],
                "children": [
                    16,
                    17,
                    15,
                    14,
                    2
                ],
                "index": 23,
                "vy": 0.000848368278885057,
                "vx": -0.0005681176317642404,
                "parent": 25
            },
            "target": {
                "id": 14,
                "x": 30.121330282550286,
                "y": 3.014955658710269,
                "type": "path",
                "radius": 3.0208333333333335,
                "paths": [
                    14
                ],
                "children": [],
                "index": 14,
                "vy": -0.005877674623064368,
                "vx": -0.00015937594982483221,
                "parent": 23
            },
            "type": "group",
            "index": 13
        },
        {
            "source": {
                "id": 23,
                "x": 38.93637264047875,
                "y": 10.778939527320984,
                "type": "group",
                "radius": 3.2737067129324986,
                "paths": [
                    14,
                    15,
                    16,
                    17,
                    2
                ],
                "children": [
                    16,
                    17,
                    15,
                    14,
                    2
                ],
                "index": 23,
                "vy": 0.000848368278885057,
                "vx": -0.0005681176317642404,
                "parent": 25
            },
            "target": {
                "id": 2,
                "x": 50.11058933056635,
                "y": 3.0169734943163005,
                "type": "path",
                "radius": 3.0208333333333335,
                "paths": [
                    2
                ],
                "children": [],
                "index": 2,
                "vy": -0.003859839017033214,
                "vx": -0.0012080100331286002,
                "parent": 23
            },
            "type": "group",
            "index": 14
        },
        {
            "source": {
                "id": 24,
                "x": 15.017053076537147,
                "y": 27.808935448410676,
                "type": "group",
                "radius": 3.336720508933034,
                "paths": [
                    0,
                    1,
                    10,
                    11,
                    18,
                    19,
                    9
                ],
                "children": [
                    9,
                    1,
                    11,
                    18,
                    19,
                    10,
                    0
                ],
                "index": 24,
                "vy": 0.000970366892198092,
                "vx": -0.0004286054698255097,
                "parent": 25
            },
            "target": {
                "id": 9,
                "x": 12.868535699275908,
                "y": 40.77441339555159,
                "type": "path",
                "radius": 3.0343366529559717,
                "paths": [
                    9
                ],
                "children": [],
                "index": 9,
                "vy": 0.001004402142779605,
                "vx": 6.366031245587135e-05,
                "parent": 24
            },
            "type": "group",
            "index": 15
        },
        {
            "source": {
                "id": 24,
                "x": 15.017053076537147,
                "y": 27.808935448410676,
                "type": "group",
                "radius": 3.336720508933034,
                "paths": [
                    0,
                    1,
                    10,
                    11,
                    18,
                    19,
                    9
                ],
                "children": [
                    9,
                    1,
                    11,
                    18,
                    19,
                    10,
                    0
                ],
                "index": 24,
                "vy": 0.000970366892198092,
                "vx": -0.0004286054698255097,
                "parent": 25
            },
            "target": {
                "id": 1,
                "x": 9.349327502092788,
                "y": 16.037713185739484,
                "type": "path",
                "radius": 3.165646729342825,
                "paths": [
                    1
                ],
                "children": [],
                "index": 1,
                "vy": 0.0009843927444493784,
                "vx": -0.000559770902959271,
                "parent": 24
            },
            "type": "group",
            "index": 16
        },
        {
            "source": {
                "id": 24,
                "x": 15.017053076537147,
                "y": 27.808935448410676,
                "type": "group",
                "radius": 3.336720508933034,
                "paths": [
                    0,
                    1,
                    10,
                    11,
                    18,
                    19,
                    9
                ],
                "children": [
                    9,
                    1,
                    11,
                    18,
                    19,
                    10,
                    0
                ],
                "index": 24,
                "vy": 0.000970366892198092,
                "vx": -0.0004286054698255097,
                "parent": 25
            },
            "target": {
                "id": 11,
                "x": 3.158581503572067,
                "y": 22.17370365383446,
                "type": "path",
                "radius": 3.0390544910453543,
                "paths": [
                    11
                ],
                "children": [],
                "index": 11,
                "vy": 0.0009906649634875387,
                "vx": -0.0005945408419398529,
                "parent": 24
            },
            "type": "group",
            "index": 17
        },
        {
            "source": {
                "id": 24,
                "x": 15.017053076537147,
                "y": 27.808935448410676,
                "type": "group",
                "radius": 3.336720508933034,
                "paths": [
                    0,
                    1,
                    10,
                    11,
                    18,
                    19,
                    9
                ],
                "children": [
                    9,
                    1,
                    11,
                    18,
                    19,
                    10,
                    0
                ],
                "index": 24,
                "vy": 0.000970366892198092,
                "vx": -0.0004286054698255097,
                "parent": 25
            },
            "target": {
                "id": 18,
                "x": 3.031255950072957,
                "y": 30.51999037279538,
                "type": "path",
                "radius": 3.0364496179042564,
                "paths": [
                    18
                ],
                "children": [],
                "index": 18,
                "vy": 0.0010700578101138513,
                "vx": -0.005193667831299571,
                "parent": 24
            },
            "type": "group",
            "index": 18
        },
        {
            "source": {
                "id": 24,
                "x": 15.017053076537147,
                "y": 27.808935448410676,
                "type": "group",
                "radius": 3.336720508933034,
                "paths": [
                    0,
                    1,
                    10,
                    11,
                    18,
                    19,
                    9
                ],
                "children": [
                    9,
                    1,
                    11,
                    18,
                    19,
                    10,
                    0
                ],
                "index": 24,
                "vy": 0.000970366892198092,
                "vx": -0.0004286054698255097,
                "parent": 25
            },
            "target": {
                "id": 19,
                "x": 5.571732442716168,
                "y": 37.698602851189335,
                "type": "path",
                "radius": 3.0355656163425615,
                "paths": [
                    19
                ],
                "children": [],
                "index": 19,
                "vy": 0.0011370105522622372,
                "vx": -0.0002570825902962745,
                "parent": 24
            },
            "type": "group",
            "index": 19
        },
        {
            "source": {
                "id": 24,
                "x": 15.017053076537147,
                "y": 27.808935448410676,
                "type": "group",
                "radius": 3.336720508933034,
                "paths": [
                    0,
                    1,
                    10,
                    11,
                    18,
                    19,
                    9
                ],
                "children": [
                    9,
                    1,
                    11,
                    18,
                    19,
                    10,
                    0
                ],
                "index": 24,
                "vy": 0.000970366892198092,
                "vx": -0.0004286054698255097,
                "parent": 25
            },
            "target": {
                "id": 10,
                "x": 18.43236558969484,
                "y": 16.304339192126484,
                "type": "path",
                "radius": 3.0203161477631966,
                "paths": [
                    10
                ],
                "children": [],
                "index": 10,
                "vy": 0.0006980658125653426,
                "vx": -0.0011264675451355705,
                "parent": 24
            },
            "type": "group",
            "index": 20
        },
        {
            "source": {
                "id": 24,
                "x": 15.017053076537147,
                "y": 27.808935448410676,
                "type": "group",
                "radius": 3.336720508933034,
                "paths": [
                    0,
                    1,
                    10,
                    11,
                    18,
                    19,
                    9
                ],
                "children": [
                    9,
                    1,
                    11,
                    18,
                    19,
                    10,
                    0
                ],
                "index": 24,
                "vy": 0.000970366892198092,
                "vx": -0.0004286054698255097,
                "parent": 25
            },
            "target": {
                "id": 0,
                "x": 22.164157084436432,
                "y": 37.02280948805595,
                "type": "path",
                "radius": 3.3364099151528737,
                "paths": [
                    0
                ],
                "children": [],
                "index": 0,
                "vy": 0.0004806888969579968,
                "vx": 0.0002862179394969057,
                "parent": 24
            },
            "type": "group",
            "index": 21
        },
        {
            "source": {
                "id": 25,
                "x": 32.57511409020525,
                "y": 24.42329898792903,
                "type": "group",
                "radius": 4.146778584144529,
                "paths": [
                    0,
                    1,
                    10,
                    11,
                    12,
                    13,
                    14,
                    15,
                    16,
                    17,
                    18,
                    19,
                    2,
                    3,
                    4,
                    5,
                    6,
                    7,
                    8,
                    9
                ],
                "children": [
                    22,
                    23,
                    24
                ],
                "index": 25,
                "vy": 0.0014909798155931255,
                "vx": -0.0004720079220475584
            },
            "target": {
                "id": 22,
                "x": 43.87703370659623,
                "y": 41.09248499195491,
                "type": "group",
                "radius": 3.8902816708484216,
                "paths": [
                    12,
                    13,
                    3,
                    4,
                    5,
                    6,
                    7,
                    8
                ],
                "children": [
                    21,
                    20
                ],
                "index": 22,
                "vy": -9.45786179647498e-05,
                "vx": -0.0001867495404099308,
                "parent": 25
            },
            "type": "group",
            "index": 22
        },
        {
            "source": {
                "id": 25,
                "x": 32.57511409020525,
                "y": 24.42329898792903,
                "type": "group",
                "radius": 4.146778584144529,
                "paths": [
                    0,
                    1,
                    10,
                    11,
                    12,
                    13,
                    14,
                    15,
                    16,
                    17,
                    18,
                    19,
                    2,
                    3,
                    4,
                    5,
                    6,
                    7,
                    8,
                    9
                ],
                "children": [
                    22,
                    23,
                    24
                ],
                "index": 25,
                "vy": 0.0014909798155931255,
                "vx": -0.0004720079220475584
            },
            "target": {
                "id": 23,
                "x": 38.93637264047875,
                "y": 10.778939527320984,
                "type": "group",
                "radius": 3.2737067129324986,
                "paths": [
                    14,
                    15,
                    16,
                    17,
                    2
                ],
                "children": [
                    16,
                    17,
                    15,
                    14,
                    2
                ],
                "index": 23,
                "vy": 0.000848368278885057,
                "vx": -0.0005681176317642404,
                "parent": 25
            },
            "type": "group",
            "index": 23
        },
        {
            "source": {
                "id": 25,
                "x": 32.57511409020525,
                "y": 24.42329898792903,
                "type": "group",
                "radius": 4.146778584144529,
                "paths": [
                    0,
                    1,
                    10,
                    11,
                    12,
                    13,
                    14,
                    15,
                    16,
                    17,
                    18,
                    19,
                    2,
                    3,
                    4,
                    5,
                    6,
                    7,
                    8,
                    9
                ],
                "children": [
                    22,
                    23,
                    24
                ],
                "index": 25,
                "vy": 0.0014909798155931255,
                "vx": -0.0004720079220475584
            },
            "target": {
                "id": 24,
                "x": 15.017053076537147,
                "y": 27.808935448410676,
                "type": "group",
                "radius": 3.336720508933034,
                "paths": [
                    0,
                    1,
                    10,
                    11,
                    18,
                    19,
                    9
                ],
                "children": [
                    9,
                    1,
                    11,
                    18,
                    19,
                    10,
                    0
                ],
                "index": 24,
                "vy": 0.000970366892198092,
                "vx": -0.0004286054698255097,
                "parent": 25
            },
            "type": "group",
            "index": 24
        }
    ]
}
